{
  "designerVersion" : "1.8.31",
  "id" : "instantiationForm",
  "name" : "instantiationForm",
  "lastUpdate" : 1548859172224,
  "rows" : [ [ {
    "type" : "formContainer",
    "dimension" : {
      "xs" : 12
    },
    "propertyValues" : { },
    "reference" : "027e43ac-cf44-4237-b6f4-c726163f2e1a",
    "hasValidationError" : false,
    "id" : "pbFormContainer",
    "container" : {
      "type" : "container",
      "dimension" : {
        "xs" : 12
      },
      "propertyValues" : { },
      "reference" : "5209964b-28bd-436d-8d31-b38668603e24",
      "hasValidationError" : false,
      "id" : "pbContainer",
      "rows" : [ [ {
        "type" : "component",
        "dimension" : {
          "md" : 12,
          "sm" : 12,
          "xs" : 12,
          "lg" : 12
        },
        "propertyValues" : {
          "removeItem" : {
            "type" : "variable"
          },
          "cssClasses" : {
            "type" : "constant",
            "value" : ""
          },
          "widgetId" : {
            "type" : "constant",
            "value" : "pbButton"
          },
          "buttonStyle" : {
            "type" : "constant",
            "value" : "primary"
          },
          "isDisplayed" : {
            "type" : "constant",
            "value" : true
          },
          "label" : {
            "type" : "interpolation",
            "value" : "Submit"
          },
          "dataToSend" : {
            "type" : "expression",
            "value" : "formOutput"
          },
          "labelHidden" : {
            "type" : "constant",
            "value" : false
          },
          "readonly" : {
            "type" : "constant",
            "value" : false
          },
          "collectionPosition" : {
            "type" : "constant"
          },
          "targetUrlOnSuccess" : {
            "type" : "interpolation",
            "value" : "/bonita"
          },
          "action" : {
            "type" : "constant",
            "value" : "Start process"
          },
          "collectionToModify" : {
            "type" : "variable"
          },
          "valueToAdd" : {
            "type" : "expression"
          },
          "disabled" : {
            "type" : "expression",
            "value" : "$form.$invalid"
          },
          "alignment" : {
            "type" : "constant",
            "value" : "center"
          },
          "class" : {
            "type" : "constant",
            "value" : "org.bonitasoft.web.designer.experimental.parametrizedWidget.ButtonWidget"
          },
          "dimension" : {
            "type" : "constant",
            "value" : 12
          }
        },
        "reference" : "dc015728-839a-4517-824f-5915477a5191",
        "hasValidationError" : false,
        "id" : "pbButton"
      } ] ]
    }
  } ] ],
  "assets" : [ {
    "id" : "48fb264e-865f-4639-99fc-b7f9dae8331a",
    "name" : "style.css",
    "type" : "css",
    "order" : 0,
    "external" : false
  }, {
    "id" : "d92e6d5d-6342-4581-9ee3-2266fe89a501",
    "name" : "localization.json",
    "type" : "json",
    "order" : 0,
    "external" : false
  } ],
  "inactiveAssets" : [ ],
  "data" : {
    "formInput" : {
      "type" : "json",
      "value" : "{ }",
      "exposed" : false
    },
    "formOutput" : {
      "type" : "expression",
      "value" : "return {\n\n};",
      "exposed" : false
    }
  },
  "hasValidationError" : false,
  "uuid" : "edd13008-14f9-4058-968e-6b3b45f152e6",
  "type" : "form",
  "description" : "Page generated with Bonita UI designer",
  "displayName" : "newForm"
}